setup.py
bentrl.egg-info/PKG-INFO
bentrl.egg-info/SOURCES.txt
bentrl.egg-info/dependency_links.txt
bentrl.egg-info/requires.txt
bentrl.egg-info/top_level.txt
gentrl/__init__.py
gentrl/dataloader.py
gentrl/decoder.py
gentrl/encoder.py
gentrl/gentrl.py
gentrl/lp.py
gentrl/tokenizer.py