Metadata-Version: 1.0
Name: bentrl
Version: 0.3
Summary: Bert-ENhanced generative Tensorial Reinforcement Learning (BENTRL)
Home-page: UNKNOWN
Author: UNKNOWN
Author-email: UNKNOWN
License: UNKNOWN
Platform: UNKNOWN
